{
  "routes": [
    {
      "item": "mobstoolforging:sword",
      "parts": [
        {
          "part_type": "sword_blade",
          "limit": 2
        },
        {
          "part_type": "sword_guard",
          "limit": 1
        },
        {
          "item_tag": "mobstoolforging:parts/handle",
          "limit": 1
        }
      ]
    },
    {
      "item": "mobstoolforging:shovel",
      "parts": [
        {
          "part_type": "shovel_head",
          "limit": 2
        },
        {
          "item_tag": "mobstoolforging:parts/handle",
          "limit": 1
        }
      ]
    },
    {
      "item": "mobstoolforging:pickaxe",
      "parts": [
        {
          "part_type": "pickaxe_head",
          "limit": 2
        },
        {
          "item_tag": "mobstoolforging:parts/handle",
          "limit": 1
        }
      ]
    },
    {
      "item": "mobstoolforging:axe",
      "parts": [
        {
          "part_type": "axe_head",
          "limit": 2
        },
        {
          "item_tag": "mobstoolforging:parts/handle",
          "limit": 1
        }
      ]
    },
    {
      "item": "mobstoolforging:hoe",
      "parts": [
        {
          "part_type": "hoe_head",
          "limit": 2
        },
        {
          "item_tag": "mobstoolforging:parts/handle",
          "limit": 1
        }
      ]
    },
    {
      "item": "mobstoolforging:mattock",
      "parts": [
        {
          "part_type": "axe_head",
          "limit": 1
        },
        {
          "part_type": "hoe_head",
          "limit": 1
        },
        {
          "item_tag": "mobstoolforging:parts/handle",
          "limit": 1
        }
      ]
    },
    {
      "item_tag": "farmersdelight:tools/knives",
      "parts": [
        {
          "part_type": "cooking_knife_head",
          "limit": 2
        },
        {
          "item_tag": "mobstoolforging:parts/handle",
          "limit": 1
        }
      ]
    },
    {
      "item": "mobstoolforging:modular_helmet",
      "parts": [
        {
          "part_type": "helmet_chainmail",
          "limit": 2
        },
        {
          "part_type": "helmet_plate",
          "limit": 2
        }
      ]
    },
    {
      "item": "mobstoolforging:modular_chestplate",
      "parts": [
        {
          "part_type": "chestplate_chainmail",
          "limit": 2
        },
        {
          "part_type": "chestplate_body",
          "limit": 2
        }
      ]
    },
    {
      "item": "mobstoolforging:modular_leggings",
      "parts": [
        {
          "part_type": "leggings_chainmail",
          "limit": 2
        },
        {
          "part_type": "leggings_plate",
          "limit": 2
        }
      ]
    },
    {
      "item": "mobstoolforging:modular_boots",
      "parts": [
        {
          "part_type": "boots_chainmail",
          "limit": 2
        },
        {
          "part_type": "boots_plate",
          "limit": 2
        }
      ]
    }
  ]
}
